[
  {
	  "label": "Manchester City",
		"value": "Manchester City",
		"link": "/man-city"
	},
	{ "label": "Chelsea", "value": "Chelsea",
		"link": "/chelsea"
	},
	{ "label": "Roma", "value": "Roma",
		"link": "/roma"
	},
	{ "label": "Sevilla", "value": "Sevilla",
		"link": "/sevilla"
	},
	{ "label": "Crystal Palace", "value": "Crystal Palace",
		"link": "/crystal-palace"
	},
	{ "label": "Bayern", "value": "Bayern",
		"link": "/bayern"
	},
	{ "label": "Genova", "value": "Genova",
		"link": "/genova"
	},
	{ "label": "Juventus", "value": "Juventus",
		"link": "/juventus"
	},
	{ "label": "Burnley FC", "value": "Burnley FC",
		"link": "/burnley-FC"
	},
	{ "label": "Palermo", "value": "Palermo",
		"link": "/palermo"
	},
	{ "label": "Swansea", "value": "Swansea",
		"link": "/swansea"
	},
	{ "label": "Liverpool", "value": "Liverpool",
		"link": "/liverpool"
	},
	{ "label": "Cagliari", "value": "Cagliari",
		"link": "/cagliari"
	},
	{ "label": "Real Madrid", "value": "Real Madrid",
		"link": "/real-madrid"
	},
	{ "label": "Tottenham Hotspur", "value": "Tottenham Hotspur",
		"link": "/tottenham-hotspur"
	},
	{ "label": "Manchester United", "value": "Manchester United",
		"link": "/man-united"
	},
	{ "label": "Watford", "value": "Watford",
		"link": "/watford"
	},
]